metric4coref/__init__.py
metric4coref/metrics.py
metric4coref-0.0.1.dist-info/LICENSE
metric4coref-0.0.1.dist-info/METADATA
metric4coref-0.0.1.dist-info/WHEEL
metric4coref-0.0.1.dist-info/top_level.txt
metric4coref-0.0.1.dist-info/RECORD
